{
  "balneario_camboriu": {
    "status": "completo",
    "fonte": "Open-Meteo Archive (best_match) — 2026-04-17",
    "periodos": {
      "madrugada": {
        "mm": 0.2,
        "classificacao": "sem_chuva"
      },
      "manha": {
        "mm": 0.2,
        "classificacao": "sem_chuva"
      },
      "tarde": {
        "mm": 1.4,
        "classificacao": "fraca"
      },
      "noite": {
        "mm": 5.1,
        "classificacao": "moderada"
      }
    },
    "total_dia": 6.9
  },
  "itajai": {
    "status": "completo",
    "fonte": "Open-Meteo Archive (best_match) — 2026-04-17",
    "periodos": {
      "madrugada": {
        "mm": 0.2,
        "classificacao": "sem_chuva"
      },
      "manha": {
        "mm": 0.3,
        "classificacao": "sem_chuva"
      },
      "tarde": {
        "mm": 0.5,
        "classificacao": "sem_chuva"
      },
      "noite": {
        "mm": 5.6,
        "classificacao": "moderada"
      }
    },
    "total_dia": 6.6
  }
}